annotyped/__init__.py
annotyped/accumulate.py
annotyped/cast.py
annotyped/checkers.py
annotyped/errors.py
annotyped-0.2.4.dist-info/METADATA
annotyped-0.2.4.dist-info/WHEEL
annotyped-0.2.4.dist-info/top_level.txt
annotyped-0.2.4.dist-info/RECORD
