Metadata-Version: 2.1
Name: annotyped
Version: 0.2.4
Summary: A lightweight library for type checking and type casting annotated vars.
Home-page: https://gitlab.com/sj1k/annotyped
Author: Steven "sj1k" Core
License: UNKNOWN
Platform: UNKNOWN
Requires-Python: >=3.5.0
